.clang-format
.flake8
.gitignore
.gitmodules
CHANGELOG.md
CODEOWNERS
CODE_OF_CONDUCT
Dockerfile
Dockerfile-cuda
Dockerfile-embedded
LICENSE
MANIFEST.in
Makefile
README.md
__init__.py
description.txt
packages.txt
setup.py
./src/opendr/__init__.py
./src/opendr/_setup.py
./src/opendr/_version.py
./src/opendr/control/__init__.py
./src/opendr/engine/__init__.py
./src/opendr/engine/constants.py
./src/opendr/engine/data.py
./src/opendr/engine/datasets.py
./src/opendr/engine/example_learner.py
./src/opendr/engine/learners.py
./src/opendr/engine/target.py
./src/opendr/perception/__init__.py
./src/opendr/perception/object_tracking_2d/__init__.py
./src/opendr/perception/object_tracking_2d/dependencies.ini
./src/opendr/perception/object_tracking_2d/logger.py
./src/opendr/perception/object_tracking_2d/datasets/.gitignore
./src/opendr/perception/object_tracking_2d/datasets/__init__.py
./src/opendr/perception/object_tracking_2d/datasets/market1501_dataset.py
./src/opendr/perception/object_tracking_2d/datasets/mot_dataset.py
./src/opendr/perception/object_tracking_2d/datasets/otb_dataset.py
./src/opendr/perception/object_tracking_2d/datasets/splits/caltech.10k.val
./src/opendr/perception/object_tracking_2d/datasets/splits/caltech.all
./src/opendr/perception/object_tracking_2d/datasets/splits/caltech.train
./src/opendr/perception/object_tracking_2d/datasets/splits/caltech.val
./src/opendr/perception/object_tracking_2d/datasets/splits/citypersons.train
./src/opendr/perception/object_tracking_2d/datasets/splits/citypersons.val
./src/opendr/perception/object_tracking_2d/datasets/splits/crowdhuman.train
./src/opendr/perception/object_tracking_2d/datasets/splits/crowdhuman.val
./src/opendr/perception/object_tracking_2d/datasets/splits/cuhksysu.train
./src/opendr/perception/object_tracking_2d/datasets/splits/cuhksysu.val
./src/opendr/perception/object_tracking_2d/datasets/splits/eth.train
./src/opendr/perception/object_tracking_2d/datasets/splits/mot15.train
./src/opendr_toolkit_object_tracking_2d.egg-info/PKG-INFO
./src/opendr_toolkit_object_tracking_2d.egg-info/SOURCES.txt
./src/opendr_toolkit_object_tracking_2d.egg-info/dependency_links.txt
./src/opendr_toolkit_object_tracking_2d.egg-info/requires.txt
./src/opendr_toolkit_object_tracking_2d.egg-info/top_level.txt
