Metadata-Version: 1.0
Name: opendr-toolkit-object-tracking-2d
Version: 3.0.0
Summary: Open Deep Learning Toolkit for Robotics (submodule: perception/object_tracking_2d)
Home-page: https://github.com/opendr-eu/opendr
Author: OpenDR consortium
Author-email: tefas@csd.auth.gr
License: LICENSE
Platform: UNKNOWN
